qmenta/__init__.py
qmenta/client/Account.py
qmenta/client/File.py
qmenta/client/Project.py
qmenta/client/Subject.py
qmenta/client/__init__.py
qmenta/client/utils.py
qmenta_client-2.0.dist-info/METADATA
qmenta_client-2.0.dist-info/WHEEL
qmenta_client-2.0.dist-info/RECORD
