Metadata-Version: 2.3
Name: qmenta-client
Version: 2.0
Summary: Python client lib to interact with the QMENTA platform.
Author: QMENTA
Author-email: dev@qmenta.com
Requires-Python: >=3.10,<4.0
Classifier: Development Status :: 4 - Beta
Classifier: Intended Audience :: Developers
Classifier: Programming Language :: Python :: 3
Classifier: Programming Language :: Python :: 3.10
Classifier: Programming Language :: Python :: 3.11
Classifier: Programming Language :: Python :: 3.12
Classifier: Programming Language :: Python :: 3.13
Requires-Dist: future (>=0.18.2,<0.19.0)
Requires-Dist: qmenta-core (>=4.0.1,<5.0.0)
Project-URL: Homepage, https://www.qmenta.com/
